{
  "tickers_requested": 2,
  "tickers_succeeded": 2,
  "tickers_failed": 0,
  "results": [
    {
      "ticker": "META",
      "output": "reports/batch_e2e/meta_earnings_report.html",
      "returncode": 0,
      "ok": true,
      "event_date": "2026-04-28",
      "regime": "Mixed / Transitional Setup",
      "top_structure": "SYMMETRIC_BUTTERFLY",
      "score": 0.9486,
      "blocking_warnings": [
        "gex_concentration_ambiguous"
      ]
    },
    {
      "ticker": "AMZN",
      "output": "reports/batch_e2e/amzn_earnings_report.html",
      "returncode": 0,
      "ok": true,
      "event_date": "2026-04-28",
      "regime": "Mixed / Transitional Setup",
      "top_structure": "SYMMETRIC_BUTTERFLY",
      "score": 0.9485,
      "blocking_warnings": [
        "gex_concentration_ambiguous"
      ]
    }
  ]
}